README.md
setup.py
Ding/__init__.py
Ding/dbot.py
Ding/dbot_test.py
Dings.egg-info/PKG-INFO
Dings.egg-info/SOURCES.txt
Dings.egg-info/dependency_links.txt
Dings.egg-info/requires.txt
Dings.egg-info/top_level.txt