Metadata-Version: 1.1
Name: Dings
Version: 1.0.0.2
Summary: Ding Ding bot.
Home-page: https://code.cloud.ysicing.net/ysicing/Ding
Author: ysicing
Author-email: ops.ysicing@gmail.com
License: LGPLv3
Keywords: Dingbot
Platform: any
Classifier: Development Status :: 3 - Alpha
Classifier: Environment :: Console :: Curses
Classifier: Intended Audience :: Developers
Classifier: License :: OSI Approved :: GNU Lesser General Public License v3 (LGPLv3)
Classifier: Programming Language :: Python :: 2.7
Classifier: Programming Language :: Python :: 3.5
Classifier: Programming Language :: Python :: 3.6
